{
    "help": "https://data.yorkopendata.org/api/3/action/help_show?name=package_show",
    "result": {
        "author": "City of York Council - Business Intelligence Hub",
        "author_email": "business.intelligence@york.gov.uk",
        "creator_user_id": "efe18669-2287-4a69-ae22-6550a21890e1",
        "extras": [
            {
                "key": "Schema",
                "value": "PollingStations"
            }
        ],
        "groups": [
            {
                "description": "Transparency",
                "display_name": "Transparency",
                "id": "7429ee4b-c1e8-4044-8aae-0b7e2c44473f",
                "image_display_url": "https://ckan.york.production.datopian.com/uploads/group/20150306-120313.6689099.png",
                "name": "transparency",
                "title": "Transparency"
            }
        ],
        "id": "cf8d4605-04f5-4685-b002-bb6a57173168",
        "isopen": true,
        "license_id": "uk-ogl",
        "license_title": "Open Government Licence 2.0 (United Kingdom)",
        "license_url": "https://www.nationalarchives.gov.uk/doc/open-government-licence/version/2/",
        "maintainer": "City of York Council - Business Intelligence Hub",
        "maintainer_email": "business.intelligence@york.gov.uk",
        "metadata_created": "2015-03-18T16:56:40.431336",
        "metadata_modified": "2020-02-13T13:59:57.765395",
        "name": "polling-stations",
        "notes": "Polling Stations in York.\r\n\r\n*Please note that the data published within this dataset is a live API link to CYC's GIS server. Any changes made to the master copy of the data will be immediately reflected in the resources of this dataset.The date shown in the \"Last Updated\" field of each GIS resource reflects when the data was first published.",
        "num_resources": 3,
        "num_tags": 0,
        "organization": {
            "approval_status": "approved",
            "created": "2015-02-23T14:47:03.256466",
            "description": "",
            "id": "6a97cf2e-7475-4521-85c6-cea1708647ba",
            "image_url": "20150223-144703.113706yorkcouncillogo.jpg",
            "is_organization": true,
            "name": "city-of-york-council",
            "revision_id": "f4fbbcee-7567-4f6d-abf8-454bebd56578",
            "state": "active",
            "title": "City of York Council",
            "type": "organization"
        },
        "owner_org": "6a97cf2e-7475-4521-85c6-cea1708647ba",
        "private": false,
        "relationships_as_object": [],
        "relationships_as_subject": [],
        "resources": [
            {
                "cache_last_updated": null,
                "cache_url": null,
                "created": "2015-03-18T17:00:51.646735",
                "datastore_active": false,
                "description": "Spreadsheet",
                "format": "CSV",
                "hash": "",
                "id": "a4541b3e-bdf4-4d32-9480-d820a76e061e",
                "last_modified": null,
                "mimetype": null,
                "mimetype_inner": null,
                "name": "Polling Stations in York",
                "package_id": "cf8d4605-04f5-4685-b002-bb6a57173168",
                "position": 0,
                "resource_type": null,
                "revision_id": "fe8a1485-6e06-4801-970a-1884937f787a",
                "size": null,
                "state": "active",
                "url": "http://data.cyc.opendata.arcgis.com/datasets/d0174d41daad4386a3727a9b1e573ace_2.csv",
                "url_type": ""
            },
            {
                "cache_last_updated": null,
                "cache_url": null,
                "created": "2015-09-17T14:39:46.430230",
                "datastore_active": false,
                "description": "KML\r\n\r\n__*Please be aware this data is very demanding and, as such, the content may take a while to load when previewing it. __\r\n\r\n__Please note that, due to slow server response, you may need to refresh the page in order to correctly preview the content.__\r\n\r\n__CYC is constantly working on improving its infrastructure to increase the performance.__",
                "format": "KML",
                "hash": "",
                "id": "f2887e76-556c-434a-885a-922cdf722dfd",
                "last_modified": null,
                "mimetype": null,
                "mimetype_inner": null,
                "name": "Polling Stations in York",
                "package_id": "cf8d4605-04f5-4685-b002-bb6a57173168",
                "position": 1,
                "resource_type": null,
                "revision_id": "624074e4-c667-4526-bcb6-12f1e8e04399",
                "size": null,
                "state": "active",
                "url": "http://data.cyc.opendata.arcgis.com/datasets/d0174d41daad4386a3727a9b1e573ace_2.kml",
                "url_type": null
            },
            {
                "cache_last_updated": null,
                "cache_url": null,
                "created": "2015-09-17T14:42:40.391661",
                "datastore_active": false,
                "description": "GeoJSON\r\n\r\n__*Please be aware this data is very demanding and, as such, the content may take a while to load when previewing it. __\r\n\r\n__Please note that, due to slow server response, you may need to refresh the page in order to correctly preview the content.__\r\n\r\n__CYC is constantly working on improving its infrastructure to increase the performance.__",
                "format": "GeoJSON",
                "hash": "",
                "id": "a11c5af6-3a72-4dba-811f-654ce86530d9",
                "last_modified": null,
                "mimetype": null,
                "mimetype_inner": null,
                "name": "Polling Stations in York",
                "package_id": "cf8d4605-04f5-4685-b002-bb6a57173168",
                "position": 2,
                "resource_type": null,
                "revision_id": "624074e4-c667-4526-bcb6-12f1e8e04399",
                "size": null,
                "state": "active",
                "url": "http://data.cyc.opendata.arcgis.com/datasets/d0174d41daad4386a3727a9b1e573ace_2.geojson",
                "url_type": null
            }
        ],
        "revision_id": "8c48d58d-43d4-4818-94ea-4ee348c448c0",
        "state": "active",
        "tags": [],
        "title": "Polling Stations in York",
        "type": "dataset",
        "url": "",
        "version": ""
    },
    "success": true
}